scoped_singleton.py
scoped_singleton-1.1.7.dist-info/LICENSE
scoped_singleton-1.1.7.dist-info/METADATA
scoped_singleton-1.1.7.dist-info/WHEEL
scoped_singleton-1.1.7.dist-info/top_level.txt
scoped_singleton-1.1.7.dist-info/RECORD
