Metadata-Version: 2.1
Name: scoped-singleton
Version: 1.1.7
Summary: Easier sharing data between objects
Home-page: https://github.com/Ed-XCF/scoped-singleton
Author: Ed__xu__Ed
Author-email: m.tofu@qq.com
License: UNKNOWN
Platform: UNKNOWN
Classifier: Programming Language :: Python :: 3
Classifier: License :: OSI Approved :: MIT License
Classifier: Operating System :: OS Independent
Requires-Python: >=3.6
